image_trimmer/__init__.py
image_trimmer/image_trimmer.py
image_trimmer-0.0.10.dist-info/METADATA
image_trimmer-0.0.10.dist-info/WHEEL
image_trimmer-0.0.10.dist-info/entry_points.txt
image_trimmer-0.0.10.dist-info/top_level.txt
image_trimmer-0.0.10.dist-info/RECORD
