Metadata-Version: 2.1
Name: image-trimmer
Version: 0.0.10
Summary: A tool to crop images and extract text using OCR
Home-page: https://github.com/jaytrairat/python-image-trimmer
Author: jaytrairat
Author-email: jaytrairat@outlook.com
Classifier: Programming Language :: Python :: 3
Requires-Dist: pytesseract
Requires-Dist: Pillow
Requires-Dist: pyyaml
